{
  "kind": "collectionType",
  "collectionName": "statistics",
  "info": {
    "singularName": "statistic",
    "pluralName": "statistics",
    "displayName": "Statistics",
    "description": ""
  },
  "options": {
    "draftAndPublish": true
  },
  "pluginOptions": {
    "i18n": {
      "localized": true
    }
  },
  "attributes": {
    "number": {
      "type": "decimal",
      "required": true
    },
    "text": {
      "type": "string",
      "pluginOptions": {
        "i18n": {
          "localized": true
        }
      },
      "required": true
    },
    "suffix": {
      "type": "string",
      "pluginOptions": {
        "i18n": {
          "localized": true
        }
      }
    }
  }
}
